audit/__init__.py
audit/admin.py
audit/models.py
audit/serializers.py
audit/tests.py
audit/urls.py
audit/views.py
audit/migrations/0001_initial.py
audit/migrations/__init__.py
dashboards/__init__.py
dashboards/admin.py
dashboards/models.py
dashboards/serializers.py
dashboards/tests.py
dashboards/urls.py
dashboards/views.py
dashboards/migrations/0001_initial.py
dashboards/migrations/0002_auto_20160922_1634.py
dashboards/migrations/0003_auto_20160927_1612.py
dashboards/migrations/0004_definition.py
dashboards/migrations/0005_auto_20170308_0831.py
dashboards/migrations/__init__.py
seed_control_interface_service/__init__.py
seed_control_interface_service/celery.py
seed_control_interface_service/settings.py
seed_control_interface_service/testsettings.py
seed_control_interface_service/urls.py
seed_control_interface_service/utils.py
seed_control_interface_service/wsgi.py
services/__init__.py
services/admin.py
services/models.py
services/serializers.py
services/tasks.py
services/tests.py
services/urls.py
services/views.py
services/migrations/0001_initial.py
services/migrations/0002_userservicetoken.py
services/migrations/0003_auto_20160813_1717.py
services/migrations/0004_auto_20160818_0750.py
services/migrations/__init__.py
services/templatetags/__init__.py
services/templatetags/seed.py
seed_control_interface_service-0.9.8.dist-info/LICENCE
seed_control_interface_service-0.9.8.dist-info/METADATA
seed_control_interface_service-0.9.8.dist-info/WHEEL
seed_control_interface_service-0.9.8.dist-info/top_level.txt
seed_control_interface_service-0.9.8.dist-info/RECORD
