Metadata-Version: 2.1
Name: seed-control-interface-service
Version: 0.9.8
Summary: Seed Control Interface Service
Home-page: http://github.com/praekelt/seed-control-interface-service
Author: Praekelt.org
Author-email: dev@praekelt.org
License: BSD
Platform: UNKNOWN
Classifier: Development Status :: 4 - Beta
Classifier: Framework :: Django
Classifier: License :: OSI Approved :: BSD License
Classifier: Programming Language :: Python
Classifier: Programming Language :: Python :: 2.7
Classifier: Topic :: Software Development :: Libraries :: Python Modules
Requires-Dist: Django (==2.2.8)
Requires-Dist: djangorestframework (==3.9.1)
Requires-Dist: coreapi (==2.3.3)
Requires-Dist: dj-database-url (==0.3.0)
Requires-Dist: psycopg2 (==2.7.1)
Requires-Dist: raven (==6.10.0)
Requires-Dist: django-filter (==2.2.0)
Requires-Dist: whitenoise (==2.0.6)
Requires-Dist: celery (==3.1.24)
Requires-Dist: django-celery (==3.3.0)
Requires-Dist: redis (==2.10.5)
Requires-Dist: pytz (==2015.7)
Requires-Dist: django-rest-hooks (==1.5.0)
Requires-Dist: seed-services-client (==0.31.0)
Requires-Dist: six (==1.10.0)
